{
  "symbol": "RELIANCE",
  "isin": "INE002A01018",
  "kind": "key-ratios",
  "url": "https://api.upstox.com/v2/fundamentals/INE002A01018/key-ratios",
  "credentialUsed": "UPSTOX_ACCESS_TOKEN",
  "status": 200,
  "statusText": "OK",
  "headers": {
    "alt-svc": "h3=\":443\"; ma=86400",
    "cache-control": "no-cache, no-store, max-age=0, must-revalidate",
    "cf-cache-status": "DYNAMIC",
    "cf-ray": "a0715043dcd85ef9-HYD",
    "connection": "keep-alive",
    "content-encoding": "br",
    "content-type": "application/json",
    "date": "Fri, 05 Jun 2026 18:41:48 GMT",
    "expires": "0",
    "pragma": "no-cache",
    "reqid": "d88924e4-3227-402a-8a56-f2ca9ed5905e",
    "requestid": "9013ecf7-f49c-4ec6-9373-59eac10d3125",
    "server": "cloudflare",
    "strict-transport-security": "max-age=0; includeSubDomains",
    "transfer-encoding": "chunked",
    "vary": "Origin, Access-Control-Request-Method, Access-Control-Request-Headers",
    "x-content-type-options": "nosniff",
    "x-frame-options": "DENY",
    "x-xss-protection": "0"
  },
  "json": {
    "status": "success",
    "data": [
      {
        "name": "P/E",
        "company_value": "22.52",
        "sector_value": "11.74"
      },
      {
        "name": "P/B",
        "company_value": "2.01",
        "sector_value": "1.44"
      },
      {
        "name": "ROA",
        "company_value": "4.88%",
        "sector_value": "7.82%"
      },
      {
        "name": "ROE",
        "company_value": "10.94%",
        "sector_value": "18.46%"
      },
      {
        "name": "ROCE",
        "company_value": "10.58%",
        "sector_value": "18.55%"
      },
      {
        "name": "Quick Ratio",
        "company_value": "0.79",
        "sector_value": "0.79"
      },
      {
        "name": "EV/EBITDA",
        "company_value": "9.99",
        "sector_value": "6.52"
      }
    ]
  }
}